<annotation>
	<folder>JPEGImages</folder>
	<filename>000080.jpg</filename>
	<path>/home/dingchao/Anaconda/SSD-0826/fullssd-keras/ssd_keras/VOC_allpics/JPEGImages/000080.jpg</path>
	<source>
		<database>Unknown</database>
	</source>
	<size>
		<width>540</width>
		<height>540</height>
		<depth>3</depth>
	</size>
	<segmented>0</segmented>
	<object>
		<name>card</name>
		<pose>Unspecified</pose>
		<truncated>0</truncated>
		<difficult>0</difficult>
		<bndbox>
			<xmin>320</xmin>
			<ymin>303</ymin>
			<xmax>471</xmax>
			<ymax>492</ymax>
		</bndbox>
	</object>
	<object>
		<name>card</name>
		<pose>Unspecified</pose>
		<truncated>0</truncated>
		<difficult>0</difficult>
		<bndbox>
			<xmin>296</xmin>
			<ymin>138</ymin>
			<xmax>469</xmax>
			<ymax>271</ymax>
		</bndbox>
	</object>
	<object>
		<name>card</name>
		<pose>Unspecified</pose>
		<truncated>0</truncated>
		<difficult>0</difficult>
		<bndbox>
			<xmin>143</xmin>
			<ymin>25</ymin>
			<xmax>316</xmax>
			<ymax>187</ymax>
		</bndbox>
	</object>
	<object>
		<name>remote</name>
		<pose>Unspecified</pose>
		<truncated>0</truncated>
		<difficult>0</difficult>
		<bndbox>
			<xmin>6</xmin>
			<ymin>174</ymin>
			<xmax>286</xmax>
			<ymax>445</ymax>
		</bndbox>
	</object>
</annotation>
